franky/__init__.py
franky/version.py
franky/analysis/__init__.py
franky/analysis/complexity_analysis.py
franky/analysis/jit_analysis.py
franky/analysis/jit_handles.py
franky/analysis/print_helper.py
franky/config/__init__.py
franky/config/config.py
franky/config/utils.py
franky/dataset/__init__.py
franky/dataset/base_dataset.py
franky/dataset/dataset_wrapper.py
franky/dataset/sampler.py
franky/dataset/utils.py
franky/device/__init__.py
franky/device/utils.py
franky/dist/__init__.py
franky/dist/dist.py
franky/dist/utils.py
franky/evaluator/__init__.py
franky/evaluator/evaluator.py
franky/evaluator/metric.py
franky/evaluator/utils.py
franky/fileio/__init__.py
franky/fileio/io.py
franky/fileio/parse.py
franky/fileio/backends/__init__.py
franky/fileio/backends/base.py
franky/fileio/backends/http_backend.py
franky/fileio/backends/local_backend.py
franky/fileio/backends/registry_utils.py
franky/fileio/handlers/__init__.py
franky/fileio/handlers/base.py
franky/fileio/handlers/json_handler.py
franky/fileio/handlers/pickle_handler.py
franky/fileio/handlers/registry_utils.py
franky/fileio/handlers/yaml_handler.py
franky/hooks/__init__.py
franky/hooks/checkpoint_hook.py
franky/hooks/ema_hook.py
franky/hooks/empty_cache_hook.py
franky/hooks/hook.py
franky/hooks/iter_timer_hook.py
franky/hooks/logger_hook.py
franky/hooks/param_scheduler_hook.py
franky/hooks/profiler_hook.py
franky/hooks/runtime_info_hook.py
franky/hooks/sampler_seed_hook.py
franky/hooks/sync_buffer_hook.py
franky/hooks/test_time_aug_hook.py
franky/infer/__init__.py
franky/infer/infer.py
franky/logging/__init__.py
franky/logging/history_buffer.py
franky/logging/logger.py
franky/logging/message_hub.py
franky/model/__init__.py
franky/model/averaged_model.py
franky/model/base_module.py
franky/model/test_time_aug.py
franky/model/utils.py
franky/model/weight_init.py
franky/model/base_model/__init__.py
franky/model/base_model/base_model.py
franky/model/wrappers/__init__.py
franky/model/wrappers/distributed.py
franky-0.0.3.dist-info/LICENSE
franky-0.0.3.dist-info/METADATA
franky-0.0.3.dist-info/WHEEL
franky-0.0.3.dist-info/top_level.txt
franky-0.0.3.dist-info/RECORD
