Metadata-Version: 2.1
Name: franky
Version: 0.0.3
Summary: Deep Learning - Engine
Author-email: Fei Wang <fei.comm@icloud.com>
License: MIT License
Project-URL: repository, https://github.com/Fei-Wang/opengine
Keywords: artificial intelligence,deep learning
Classifier: Development Status :: 4 - Beta
Classifier: Intended Audience :: Developers
Classifier: Topic :: Scientific/Engineering :: Artificial Intelligence
Classifier: License :: OSI Approved :: MIT License
Classifier: Programming Language :: Python :: 3
Classifier: Operating System :: OS Independent
Requires-Python: >=3.8
License-File: LICENSE
Requires-Dist: numpy (==1.24.2)
Requires-Dist: torch (==1.13.1)
Requires-Dist: packaging (==23.0)
Requires-Dist: addict (==2.4.0)
Requires-Dist: yapf (==0.32.0)
Requires-Dist: PyYAML (==6.0)
Requires-Dist: termcolor (==2.2.0)
Requires-Dist: rich (==13.3.1)
